benchmarks/__init__.py
benchmarks/benchmarks.py
gnss/__init__.py
gnss/coord_system.py
gnss-0.3.1.dist-info/DESCRIPTION.rst
gnss-0.3.1.dist-info/METADATA
gnss-0.3.1.dist-info/RECORD
gnss-0.3.1.dist-info/WHEEL
gnss-0.3.1.dist-info/metadata.json
gnss-0.3.1.dist-info/top_level.txt
