Metadata-Version: 2.0
Name: gnss
Version: 0.3.1
Summary: GNSS Utilities
Home-page: https://github.com/swift-nav/pygnss
Author: Swift Navigation
Author-email: dev@swiftnav.com
License: mit
Platform: UNKNOWN
Classifier: License :: OSI Approved :: MIT License
Classifier: Programming Language :: Python
Classifier: Programming Language :: Python :: 2.7
Classifier: Programming Language :: Python :: 3
Classifier: Programming Language :: Python :: 3.6
Requires-Dist: numpy
Provides-Extra: test
Requires-Dist: pytest; extra == 'test'
Requires-Dist: hypothesis; extra == 'test'
